allauth_sms/__init__.py
allauth_sms/forms.py
allauth_sms/models.py
allauth_sms/provider.py
allauth_sms/urls.py
allauth_sms/views.py
allauth_sms/migrations/0001_initial.py
allauth_sms/migrations/__init__.py
django_allauth_sms-0.1.0.dist-info/LICENSE
django_allauth_sms-0.1.0.dist-info/METADATA
django_allauth_sms-0.1.0.dist-info/WHEEL
django_allauth_sms-0.1.0.dist-info/top_level.txt
django_allauth_sms-0.1.0.dist-info/RECORD
